{
  "_class": "shapePath",
  "booleanOperation": -1,
  "do_objectID": "2131C566-8586-4C26-A64E-0715C9D043A7",
  "edited": true,
  "exportOptions": {
    "_class": "exportOptions",
    "exportFormats": [
    ],
    "includedLayerIds": [
    ],
    "layerOptions": 0,
    "shouldTrim": false
  },
  "frame": {
    "_class": "rect",
    "constrainProportions": false,
    "height": 3.185142857142857,
    "width": 2.285714285714288,
    "x": 11.41371428571429,
    "y": 5.194285714285716
  },
  "isClosed": true,
  "isFlippedHorizontal": false,
  "isFlippedVertical": false,
  "isLocked": false,
  "isVisible": true,
  "layerListExpandedType": 0,
  "name": "Path",
  "nameIsFixed": false,
  "path": {
    "_class": "path",
    "isClosed": true,
    "pointRadiusBehaviour": 1,
    "points": [
      {
        "_class": "curvePoint",
        "cornerRadius": 0,
        "curveFrom": "{1, 0}",
        "curveMode": 1,
        "curveTo": "{1, 0}",
        "hasCurveFrom": false,
        "hasCurveTo": false,
        "point": "{1, 0}"
      },
      {
        "_class": "curvePoint",
        "cornerRadius": 0,
        "curveFrom": "{0, 0.28238249013275923}",
        "curveMode": 1,
        "curveTo": "{0, 0.28238249013275923}",
        "hasCurveFrom": false,
        "hasCurveTo": false,
        "point": "{0, 0.28238249013275923}"
      },
      {
        "_class": "curvePoint",
        "cornerRadius": 0,
        "curveFrom": "{0, 1}",
        "curveMode": 1,
        "curveTo": "{0, 1}",
        "hasCurveFrom": false,
        "hasCurveTo": false,
        "point": "{0, 1}"
      },
      {
        "_class": "curvePoint",
        "cornerRadius": 0,
        "curveFrom": "{1, 0.71761750986724082}",
        "curveMode": 1,
        "curveTo": "{1, 0.71761750986724082}",
        "hasCurveFrom": false,
        "hasCurveTo": false,
        "point": "{1, 0.71761750986724082}"
      }
    ]
  },
  "pointRadiusBehaviour": 1,
  "points": [
    {
      "_class": "curvePoint",
      "cornerRadius": 0,
      "curveFrom": "{1, 0}",
      "curveMode": 1,
      "curveTo": "{1, 0}",
      "hasCurveFrom": false,
      "hasCurveTo": false,
      "point": "{1, 0}"
    },
    {
      "_class": "curvePoint",
      "cornerRadius": 0,
      "curveFrom": "{0, 0.28238249013275923}",
      "curveMode": 1,
      "curveTo": "{0, 0.28238249013275923}",
      "hasCurveFrom": false,
      "hasCurveTo": false,
      "point": "{0, 0.28238249013275923}"
    },
    {
      "_class": "curvePoint",
      "cornerRadius": 0,
      "curveFrom": "{0, 1}",
      "curveMode": 1,
      "curveTo": "{0, 1}",
      "hasCurveFrom": false,
      "hasCurveTo": false,
      "point": "{0, 1}"
    },
    {
      "_class": "curvePoint",
      "cornerRadius": 0,
      "curveFrom": "{1, 0.71761750986724082}",
      "curveMode": 1,
      "curveTo": "{1, 0.71761750986724082}",
      "hasCurveFrom": false,
      "hasCurveTo": false,
      "point": "{1, 0.71761750986724082}"
    }
  ],
  "resizingConstraint": 63,
  "resizingType": 0,
  "rotation": 0,
  "shouldBreakMaskChain": false
}