{
  "_class": "symbolMaster",
  "backgroundColor": {
    "_class": "color",
    "alpha": 1,
    "blue": 1,
    "do_objectID": "74E69434-8447-42E6-ADB7-778AB1665BA7",
    "green": 1,
    "red": 1
  },
  "changeIdentifier": 1044,
  "do_objectID": "F0CD6D3C-778A-464A-BEC7-6BB3BE37901F",
  "exportOptions": {
    "_class": "exportOptions",
    "do_objectID": "AC22E37B-AF30-4C2B-B1D3-04BE2377C424",
    "exportFormats": [
    ],
    "includedLayerIds": [
    ],
    "layerOptions": 0,
    "shouldTrim": false
  },
  "frame": {
    "_class": "rect",
    "constrainProportions": false,
    "do_objectID": "EEC75282-3C95-4219-848E-6394F739D0D7",
    "height": 9,
    "width": 13,
    "x": -283,
    "y": 170
  },
  "hasBackgroundColor": false,
  "hasClickThrough": false,
  "horizontalRulerData": {
    "_class": "rulerData",
    "base": 0,
    "do_objectID": "8665A5B3-0D94-4B77-83ED-DBB936EDD597",
    "guides": [
    ]
  },
  "includeBackgroundColorInExport": true,
  "includeBackgroundColorInInstance": true,
  "includeInCloudUpload": true,
  "isFlippedHorizontal": false,
  "isFlippedVertical": false,
  "isFlowHome": false,
  "isLocked": false,
  "isVisible": true,
  "layerListExpandedType": 0,
  "layers": [
    {
      "class": "symbolInstance",
      "id": "21C68D1A-3886-4038-B0E3-9F3C14E855F8"
    }
  ],
  "name": "/6 Danger",
  "nameIsFixed": true,
  "resizesContent": true,
  "resizingConstraint": 63,
  "resizingType": 0,
  "rotation": 0,
  "shouldBreakMaskChain": true,
  "style": {
    "_class": "style",
    "do_objectID": "5234877E-92B9-4FBE-979A-13F9B970A2C8",
    "endDecorationType": 0,
    "miterLimit": 10,
    "startDecorationType": 0
  },
  "symbolID": "C5412AA9-CD33-4DC5-866E-579FEB2FBBCD",
  "verticalRulerData": {
    "_class": "rulerData",
    "base": 0,
    "do_objectID": "57FA5990-B6AB-44CC-AC0D-3984B659C6E9",
    "guides": [
    ]
  }
}